{
  "field" : "polygon60",
  "symmetry" : "octahedral",
  "orientations" : [ [ 1.0, 0.0, 0.0, 0.0, 0.0, 1.0, 0.0, 0.0, 0.0, 0.0, 1.0, 0.0, 0.0, 0.0, 0.0, 1.0 ], [ 1.0, 0.0, 0.0, 0.0, 0.0, 0.0, 1.0, 0.0, 0.0, -1.0, 0.0, 0.0, 0.0, 0.0, 0.0, 1.0 ], [ 1.0, 0.0, 0.0, 0.0, 0.0, -1.0, 0.0, 0.0, 0.0, 0.0, -1.0, 0.0, 0.0, 0.0, 0.0, 1.0 ], [ 1.0, 0.0, 0.0, 0.0, 0.0, 0.0, -1.0, 0.0, 0.0, 1.0, 0.0, 0.0, 0.0, 0.0, 0.0, 1.0 ], [ 0.0, 1.0, 0.0, 0.0, 0.0, 0.0, 1.0, 0.0, 1.0, 0.0, 0.0, 0.0, 0.0, 0.0, 0.0, 1.0 ], [ 0.0, 1.0, 0.0, 0.0, 1.0, 0.0, 0.0, 0.0, 0.0, 0.0, -1.0, 0.0, 0.0, 0.0, 0.0, 1.0 ], [ 0.0, 1.0, 0.0, 0.0, 0.0, 0.0, -1.0, 0.0, -1.0, 0.0, 0.0, 0.0, 0.0, 0.0, 0.0, 1.0 ], [ 0.0, 1.0, 0.0, 0.0, -1.0, 0.0, 0.0, 0.0, 0.0, 0.0, 1.0, 0.0, 0.0, 0.0, 0.0, 1.0 ], [ 0.0, 0.0, 1.0, 0.0, 1.0, 0.0, 0.0, 0.0, 0.0, 1.0, 0.0, 0.0, 0.0, 0.0, 0.0, 1.0 ], [ 0.0, 0.0, 1.0, 0.0, 0.0, 1.0, 0.0, 0.0, -1.0, 0.0, 0.0, 0.0, 0.0, 0.0, 0.0, 1.0 ], [ 0.0, 0.0, 1.0, 0.0, -1.0, 0.0, 0.0, 0.0, 0.0, -1.0, 0.0, 0.0, 0.0, 0.0, 0.0, 1.0 ], [ 0.0, 0.0, 1.0, 0.0, 0.0, -1.0, 0.0, 0.0, 1.0, 0.0, 0.0, 0.0, 0.0, 0.0, 0.0, 1.0 ], [ -1.0, 0.0, 0.0, 0.0, 0.0, -1.0, 0.0, 0.0, 0.0, 0.0, 1.0, 0.0, 0.0, 0.0, 0.0, 1.0 ], [ -1.0, 0.0, 0.0, 0.0, 0.0, 0.0, 1.0, 0.0, 0.0, 1.0, 0.0, 0.0, 0.0, 0.0, 0.0, 1.0 ], [ -1.0, 0.0, 0.0, 0.0, 0.0, 1.0, 0.0, 0.0, 0.0, 0.0, -1.0, 0.0, 0.0, 0.0, 0.0, 1.0 ], [ -1.0, 0.0, 0.0, 0.0, 0.0, 0.0, -1.0, 0.0, 0.0, -1.0, 0.0, 0.0, 0.0, 0.0, 0.0, 1.0 ], [ 0.0, -1.0, 0.0, 0.0, 0.0, 0.0, -1.0, 0.0, 1.0, 0.0, 0.0, 0.0, 0.0, 0.0, 0.0, 1.0 ], [ 0.0, -1.0, 0.0, 0.0, 1.0, 0.0, 0.0, 0.0, 0.0, 0.0, 1.0, 0.0, 0.0, 0.0, 0.0, 1.0 ], [ 0.0, -1.0, 0.0, 0.0, 0.0, 0.0, 1.0, 0.0, -1.0, 0.0, 0.0, 0.0, 0.0, 0.0, 0.0, 1.0 ], [ 0.0, -1.0, 0.0, 0.0, -1.0, 0.0, 0.0, 0.0, 0.0, 0.0, -1.0, 0.0, 0.0, 0.0, 0.0, 1.0 ], [ 0.0, 0.0, -1.0, 0.0, -1.0, 0.0, 0.0, 0.0, 0.0, 1.0, 0.0, 0.0, 0.0, 0.0, 0.0, 1.0 ], [ 0.0, 0.0, -1.0, 0.0, 0.0, 1.0, 0.0, 0.0, 1.0, 0.0, 0.0, 0.0, 0.0, 0.0, 0.0, 1.0 ], [ 0.0, 0.0, -1.0, 0.0, 1.0, 0.0, 0.0, 0.0, 0.0, -1.0, 0.0, 0.0, 0.0, 0.0, 0.0, 1.0 ], [ 0.0, 0.0, -1.0, 0.0, 0.0, -1.0, 0.0, 0.0, -1.0, 0.0, 0.0, 0.0, 0.0, 0.0, 0.0, 1.0 ] ],
  "lights" : {
    "backgroundColor" : "#DBDBFF",
    "ambientColor" : "#292929",
    "directionalLights" : [ {
      "direction" : {
        "x" : 1.0,
        "y" : -1.0,
        "z" : -1.0
      },
      "color" : "#EBEBE4"
    }, {
      "direction" : {
        "x" : -1.0,
        "y" : 0.0,
        "z" : 0.0
      },
      "color" : "#E4E4EB"
    }, {
      "direction" : {
        "x" : 0.0,
        "y" : 0.0,
        "z" : -1.0
      },
      "color" : "#1E1E1E"
    } ]
  },
  "camera" : {
    "width" : 33.460827,
    "stereo" : false,
    "lookDirection" : {
      "x" : -0.70710677,
      "y" : 0.70710677,
      "z" : 0.0
    },
    "upDirection" : {
      "x" : 0.57735026,
      "y" : 0.57735026,
      "z" : -0.57735026
    },
    "lookAtPoint" : {
      "x" : 0.0,
      "y" : 0.0,
      "z" : 0.0
    },
    "viewDistance" : 74.357124,
    "nearClipDistance" : 0.18589294,
    "farClipDistance" : 148.71391,
    "fieldOfView" : 0.44263044,
    "perspective" : false,
    "position" : {
      "x" : 52.578426,
      "y" : -52.578426,
      "z" : 0.0
    }
  },
  "embedding" : [ 1.0, 0.0, 0.0, 0.0, 0.0, 1.0, 0.0, 0.0, 0.0, 0.0, 1.0, 0.0, 0.0, 0.0, 0.0, 1.0 ],
  "shapes" : [ {
    "id" : "8831d3d1-717a-4f33-b37e-f688cd59eade",
    "vertices" : [ {
      "x" : 1.8778762,
      "y" : 1.8778762,
      "z" : -7.5115047
    }, {
      "x" : 5.6336284,
      "y" : 0.0,
      "z" : -5.6336284
    }, {
      "x" : 5.3114357,
      "y" : -2.6557178,
      "z" : -5.3114357
    }, {
      "x" : 0.0,
      "y" : 0.0,
      "z" : -7.967154
    } ],
    "faces" : [ {
      "vertices" : [ 0, 1, 2 ]
    }, {
      "vertices" : [ 0, 2, 3 ]
    }, {
      "vertices" : [ 0, 3, 2 ]
    }, {
      "vertices" : [ 0, 2, 1 ]
    } ]
  }, {
    "id" : "37df7afd-353c-4ab6-afff-57f11ec9131f",
    "vertices" : [ {
      "x" : 0.5013733,
      "y" : 0.0,
      "z" : 0.0
    }, {
      "x" : -0.5013733,
      "y" : 0.0,
      "z" : 0.0
    }, {
      "x" : 0.0,
      "y" : 0.5013733,
      "z" : 0.0
    }, {
      "x" : 0.0,
      "y" : -0.5013733,
      "z" : 0.0
    }, {
      "x" : 0.0,
      "y" : 0.0,
      "z" : 0.5013733
    }, {
      "x" : 0.0,
      "y" : 0.0,
      "z" : -0.5013733
    } ],
    "faces" : [ {
      "vertices" : [ 0, 2, 4 ]
    }, {
      "vertices" : [ 0, 5, 2 ]
    }, {
      "vertices" : [ 0, 4, 3 ]
    }, {
      "vertices" : [ 1, 4, 2 ]
    }, {
      "vertices" : [ 0, 3, 5 ]
    }, {
      "vertices" : [ 1, 2, 5 ]
    }, {
      "vertices" : [ 1, 3, 4 ]
    }, {
      "vertices" : [ 1, 5, 3 ]
    } ]
  }, {
    "id" : "3d88162b-b08c-4059-951c-79167ca70f8f",
    "vertices" : [ {
      "x" : 2.6557178,
      "y" : -5.3114357,
      "z" : 5.3114357
    }, {
      "x" : 4.5998383,
      "y" : -4.5998383,
      "z" : 4.5998383
    }, {
      "x" : 5.6336284,
      "y" : 0.0,
      "z" : 5.6336284
    } ],
    "faces" : [ {
      "vertices" : [ 0, 1, 2 ]
    }, {
      "vertices" : [ 0, 2, 1 ]
    } ]
  }, {
    "id" : "ae6d8e5c-1b79-4358-9979-cddd44a68e2c",
    "vertices" : [ {
      "x" : -5.3114357,
      "y" : -5.3114357,
      "z" : -2.6557178
    }, {
      "x" : -4.5998383,
      "y" : -4.5998383,
      "z" : -4.5998383
    }, {
      "x" : 0.0,
      "y" : -5.6336284,
      "z" : -5.6336284
    } ],
    "faces" : [ {
      "vertices" : [ 0, 1, 2 ]
    }, {
      "vertices" : [ 0, 2, 1 ]
    } ]
  }, {
    "id" : "ae3b6adb-44f5-4937-8bb5-911baacedd85",
    "vertices" : [ {
      "x" : 5.6336284,
      "y" : 0.0,
      "z" : 5.6336284
    }, {
      "x" : 0.0,
      "y" : 0.0,
      "z" : 7.967154
    }, {
      "x" : 4.5998383,
      "y" : 4.5998383,
      "z" : 4.5998383
    } ],
    "faces" : [ {
      "vertices" : [ 0, 1, 2 ]
    }, {
      "vertices" : [ 0, 2, 1 ]
    } ]
  }, {
    "id" : "ac2bcaca-4e04-4f67-b58a-a59931c18a4b",
    "vertices" : [ {
      "x" : -5.3114357,
      "y" : -5.3114357,
      "z" : -2.6557178
    }, {
      "x" : -5.6336284,
      "y" : -5.6336284,
      "z" : 0.0
    }, {
      "x" : -7.5115047,
      "y" : -1.8778762,
      "z" : 1.8778762
    }, {
      "x" : -7.967154,
      "y" : 0.0,
      "z" : 0.0
    } ],
    "faces" : [ {
      "vertices" : [ 0, 1, 2 ]
    }, {
      "vertices" : [ 0, 2, 3 ]
    }, {
      "vertices" : [ 0, 3, 2 ]
    }, {
      "vertices" : [ 0, 2, 1 ]
    } ]
  }, {
    "id" : "9e535c97-b82f-4592-8c89-74e628f274cd",
    "vertices" : [ {
      "x" : 4.5998383,
      "y" : -4.5998383,
      "z" : 4.5998383
    }, {
      "x" : 7.967154,
      "y" : 0.0,
      "z" : 0.0
    }, {
      "x" : 5.6336284,
      "y" : -5.6336284,
      "z" : 0.0
    } ],
    "faces" : [ {
      "vertices" : [ 0, 1, 2 ]
    }, {
      "vertices" : [ 0, 2, 1 ]
    } ]
  }, {
    "id" : "ed2e9538-f6dd-440e-b8c4-8364cfea64e2",
    "vertices" : [ {
      "x" : -5.6336284,
      "y" : 0.0,
      "z" : 5.6336284
    }, {
      "x" : -7.5115047,
      "y" : -1.8778762,
      "z" : 1.8778762
    }, {
      "x" : -4.5998383,
      "y" : -4.5998383,
      "z" : 4.5998383
    } ],
    "faces" : [ {
      "vertices" : [ 0, 1, 2 ]
    }, {
      "vertices" : [ 0, 2, 1 ]
    } ]
  }, {
    "id" : "dac3063f-28a7-41b0-a1bb-46a277882306",
    "vertices" : [ {
      "x" : -4.5998383,
      "y" : 4.5998383,
      "z" : 4.5998383
    }, {
      "x" : 0.0,
      "y" : 7.967154,
      "z" : 0.0
    }, {
      "x" : 0.0,
      "y" : 5.6336284,
      "z" : 5.6336284
    } ],
    "faces" : [ {
      "vertices" : [ 0, 1, 2 ]
    }, {
      "vertices" : [ 0, 2, 1 ]
    } ]
  }, {
    "id" : "71d4bade-199b-4087-a425-817a81da87b4",
    "vertices" : [ {
      "x" : -5.6336284,
      "y" : 5.6336284,
      "z" : 0.0
    }, {
      "x" : -7.967154,
      "y" : 0.0,
      "z" : 0.0
    }, {
      "x" : -4.5998383,
      "y" : 4.5998383,
      "z" : -4.5998383
    } ],
    "faces" : [ {
      "vertices" : [ 0, 1, 2 ]
    }, {
      "vertices" : [ 0, 2, 1 ]
    } ]
  }, {
    "id" : "f52e5f75-b5a9-41e7-80e5-6fb37478c352",
    "vertices" : [ {
      "x" : 1.8778762,
      "y" : 1.8778762,
      "z" : -7.5115047
    }, {
      "x" : 0.0,
      "y" : 5.6336284,
      "z" : -5.6336284
    }, {
      "x" : 4.5998383,
      "y" : 4.5998383,
      "z" : -4.5998383
    } ],
    "faces" : [ {
      "vertices" : [ 0, 1, 2 ]
    }, {
      "vertices" : [ 0, 2, 1 ]
    } ]
  }, {
    "id" : "36342bf4-a482-42dd-be91-c5a0c364798c",
    "vertices" : [ {
      "x" : -1.8778762,
      "y" : -1.8778762,
      "z" : 7.5115047
    }, {
      "x" : -5.6336284,
      "y" : 0.0,
      "z" : 5.6336284
    }, {
      "x" : -4.5998383,
      "y" : -4.5998383,
      "z" : 4.5998383
    } ],
    "faces" : [ {
      "vertices" : [ 0, 1, 2 ]
    }, {
      "vertices" : [ 0, 2, 1 ]
    } ]
  }, {
    "id" : "718d5dd3-0cdd-435b-9228-1f3b9af6a50a",
    "vertices" : [ {
      "x" : 2.6557178,
      "y" : -5.3114357,
      "z" : 5.3114357
    }, {
      "x" : 0.0,
      "y" : 0.0,
      "z" : 7.967154
    }, {
      "x" : -1.8778762,
      "y" : -1.8778762,
      "z" : 7.5115047
    }, {
      "x" : 0.0,
      "y" : -5.6336284,
      "z" : 5.6336284
    } ],
    "faces" : [ {
      "vertices" : [ 0, 1, 2 ]
    }, {
      "vertices" : [ 0, 2, 3 ]
    }, {
      "vertices" : [ 0, 3, 2 ]
    }, {
      "vertices" : [ 0, 2, 1 ]
    } ]
  }, {
    "id" : "75e9cbba-e42f-4aee-94a9-2ecd302157e4",
    "vertices" : [ {
      "x" : 5.3114357,
      "y" : -2.6557178,
      "z" : -5.3114357
    }, {
      "x" : 5.6336284,
      "y" : 0.0,
      "z" : -5.6336284
    }, {
      "x" : 7.5115047,
      "y" : 1.8778762,
      "z" : -1.8778762
    }, {
      "x" : 7.967154,
      "y" : 0.0,
      "z" : 0.0
    } ],
    "faces" : [ {
      "vertices" : [ 0, 1, 2 ]
    }, {
      "vertices" : [ 0, 2, 3 ]
    }, {
      "vertices" : [ 0, 3, 2 ]
    }, {
      "vertices" : [ 0, 2, 1 ]
    } ]
  }, {
    "id" : "d92f8a65-cd28-456e-b1e7-3271dd07b210",
    "vertices" : [ {
      "x" : -5.3114357,
      "y" : -5.3114357,
      "z" : -2.6557178
    }, {
      "x" : 0.0,
      "y" : -5.6336284,
      "z" : -5.6336284
    }, {
      "x" : 0.0,
      "y" : -7.967154,
      "z" : 0.0
    } ],
    "faces" : [ {
      "vertices" : [ 0, 1, 2 ]
    }, {
      "vertices" : [ 0, 2, 1 ]
    } ]
  }, {
    "id" : "3f262954-a4fb-4fd7-8744-aec6dc2c34d2",
    "vertices" : [ {
      "x" : -2.6557178,
      "y" : 5.3114357,
      "z" : -5.3114357
    }, {
      "x" : 0.0,
      "y" : 7.967154,
      "z" : 0.0
    }, {
      "x" : 1.8778762,
      "y" : 7.5115047,
      "z" : -1.8778762
    }, {
      "x" : 0.0,
      "y" : 5.6336284,
      "z" : -5.6336284
    } ],
    "faces" : [ {
      "vertices" : [ 0, 1, 2 ]
    }, {
      "vertices" : [ 0, 2, 3 ]
    }, {
      "vertices" : [ 0, 3, 2 ]
    }, {
      "vertices" : [ 0, 2, 1 ]
    } ]
  }, {
    "id" : "5014e9d8-e2f2-4bc3-b322-f19923101982",
    "vertices" : [ {
      "x" : -7.5115047,
      "y" : -1.8778762,
      "z" : 1.8778762
    }, {
      "x" : -5.6336284,
      "y" : -5.6336284,
      "z" : 0.0
    }, {
      "x" : -4.5998383,
      "y" : -4.5998383,
      "z" : 4.5998383
    } ],
    "faces" : [ {
      "vertices" : [ 0, 1, 2 ]
    }, {
      "vertices" : [ 0, 2, 1 ]
    } ]
  }, {
    "id" : "d0e05b00-8f11-4056-9729-57dcdda1c7ee",
    "vertices" : [ {
      "x" : -5.3114357,
      "y" : 2.6557178,
      "z" : 5.3114357
    }, {
      "x" : -5.6336284,
      "y" : 0.0,
      "z" : 5.6336284
    }, {
      "x" : -1.8778762,
      "y" : -1.8778762,
      "z" : 7.5115047
    }, {
      "x" : 0.0,
      "y" : 0.0,
      "z" : 7.967154
    } ],
    "faces" : [ {
      "vertices" : [ 0, 1, 2 ]
    }, {
      "vertices" : [ 0, 2, 3 ]
    }, {
      "vertices" : [ 0, 3, 2 ]
    }, {
      "vertices" : [ 0, 2, 1 ]
    } ]
  }, {
    "id" : "dd13bcf9-4a07-4a60-b2ad-dd9a0149d3b2",
    "vertices" : [ {
      "x" : -5.3114357,
      "y" : 2.6557178,
      "z" : 5.3114357
    }, {
      "x" : 0.0,
      "y" : 5.6336284,
      "z" : 5.6336284
    }, {
      "x" : -4.5998383,
      "y" : 4.5998383,
      "z" : 4.5998383
    } ],
    "faces" : [ {
      "vertices" : [ 0, 1, 2 ]
    }, {
      "vertices" : [ 0, 2, 1 ]
    } ]
  }, {
    "id" : "a0e0c217-88e4-406e-b92b-d0fd971feea2",
    "vertices" : [ {
      "x" : -5.6336284,
      "y" : 5.6336284,
      "z" : 0.0
    }, {
      "x" : -5.3114357,
      "y" : 2.6557178,
      "z" : 5.3114357
    }, {
      "x" : -4.5998383,
      "y" : 4.5998383,
      "z" : 4.5998383
    } ],
    "faces" : [ {
      "vertices" : [ 0, 1, 2 ]
    }, {
      "vertices" : [ 0, 2, 1 ]
    } ]
  }, {
    "id" : "eba009e8-8b42-485d-aded-d0aabc05b740",
    "vertices" : [ {
      "x" : -5.6336284,
      "y" : 0.0,
      "z" : -5.6336284
    }, {
      "x" : -4.5998383,
      "y" : -4.5998383,
      "z" : -4.5998383
    }, {
      "x" : -5.3114357,
      "y" : -5.3114357,
      "z" : -2.6557178
    } ],
    "faces" : [ {
      "vertices" : [ 0, 1, 2 ]
    }, {
      "vertices" : [ 0, 2, 1 ]
    } ]
  }, {
    "id" : "4941e416-eb94-472d-8134-cd399de6f072",
    "vertices" : [ {
      "x" : -5.6336284,
      "y" : 5.6336284,
      "z" : 0.0
    }, {
      "x" : -7.967154,
      "y" : 0.0,
      "z" : 0.0
    }, {
      "x" : -5.3114357,
      "y" : 2.6557178,
      "z" : 5.3114357
    } ],
    "faces" : [ {
      "vertices" : [ 0, 1, 2 ]
    }, {
      "vertices" : [ 0, 2, 1 ]
    } ]
  }, {
    "id" : "5ee63fb7-e96f-41c3-8008-f818a5aa3aeb",
    "vertices" : [ {
      "x" : 5.3114357,
      "y" : -2.6557178,
      "z" : -5.3114357
    }, {
      "x" : 4.5998383,
      "y" : -4.5998383,
      "z" : -4.5998383
    }, {
      "x" : 0.0,
      "y" : -5.6336284,
      "z" : -5.6336284
    } ],
    "faces" : [ {
      "vertices" : [ 0, 1, 2 ]
    }, {
      "vertices" : [ 0, 2, 1 ]
    } ]
  }, {
    "id" : "dc8cacfc-dd32-4fce-9fa0-000ebe8f6bb1",
    "vertices" : [ {
      "x" : -5.3114357,
      "y" : -5.3114357,
      "z" : -2.6557178
    }, {
      "x" : 0.0,
      "y" : -7.967154,
      "z" : 0.0
    }, {
      "x" : -1.8778762,
      "y" : -7.5115047,
      "z" : 1.8778762
    }, {
      "x" : -5.6336284,
      "y" : -5.6336284,
      "z" : 0.0
    } ],
    "faces" : [ {
      "vertices" : [ 0, 1, 2 ]
    }, {
      "vertices" : [ 0, 2, 3 ]
    }, {
      "vertices" : [ 0, 3, 2 ]
    }, {
      "vertices" : [ 0, 2, 1 ]
    } ]
  }, {
    "id" : "4986bdb6-750a-4d89-9bee-62098c2f3d0f",
    "vertices" : [ {
      "x" : 1.8778762,
      "y" : 7.5115047,
      "z" : -1.8778762
    }, {
      "x" : 4.5998383,
      "y" : 4.5998383,
      "z" : -4.5998383
    }, {
      "x" : 0.0,
      "y" : 5.6336284,
      "z" : -5.6336284
    } ],
    "faces" : [ {
      "vertices" : [ 0, 1, 2 ]
    }, {
      "vertices" : [ 0, 2, 1 ]
    } ]
  }, {
    "id" : "094bc9ca-a4b0-48cb-8e0c-77a4e1087998",
    "vertices" : [ {
      "x" : -4.5998383,
      "y" : -4.5998383,
      "z" : -4.5998383
    }, {
      "x" : 0.0,
      "y" : 0.0,
      "z" : -7.967154
    }, {
      "x" : -5.6336284,
      "y" : 0.0,
      "z" : -5.6336284
    } ],
    "faces" : [ {
      "vertices" : [ 0, 1, 2 ]
    }, {
      "vertices" : [ 0, 2, 1 ]
    } ]
  }, {
    "id" : "88199e92-0120-4365-a675-edc8ab7ee882",
    "vertices" : [ {
      "x" : -4.5998383,
      "y" : 4.5998383,
      "z" : 4.5998383
    }, {
      "x" : -5.6336284,
      "y" : 5.6336284,
      "z" : 0.0
    }, {
      "x" : 0.0,
      "y" : 7.967154,
      "z" : 0.0
    } ],
    "faces" : [ {
      "vertices" : [ 0, 1, 2 ]
    }, {
      "vertices" : [ 0, 2, 1 ]
    } ]
  }, {
    "id" : "bf93f6b4-4b84-44bb-99ea-91edacc5363c",
    "vertices" : [ {
      "x" : 5.3114357,
      "y" : 5.3114357,
      "z" : 2.6557178
    }, {
      "x" : 5.6336284,
      "y" : 0.0,
      "z" : 5.6336284
    }, {
      "x" : 7.967154,
      "y" : 0.0,
      "z" : 0.0
    } ],
    "faces" : [ {
      "vertices" : [ 0, 1, 2 ]
    }, {
      "vertices" : [ 0, 2, 1 ]
    } ]
  }, {
    "id" : "9e31514b-4178-417d-a5d3-5d395728d700",
    "vertices" : [ {
      "x" : -1.8778762,
      "y" : -7.5115047,
      "z" : 1.8778762
    }, {
      "x" : -4.5998383,
      "y" : -4.5998383,
      "z" : 4.5998383
    }, {
      "x" : -5.6336284,
      "y" : -5.6336284,
      "z" : 0.0
    } ],
    "faces" : [ {
      "vertices" : [ 0, 1, 2 ]
    }, {
      "vertices" : [ 0, 2, 1 ]
    } ]
  }, {
    "id" : "f32b3079-b201-460e-a179-39595de87291",
    "vertices" : [ {
      "x" : -1.8778762,
      "y" : -7.5115047,
      "z" : 1.8778762
    }, {
      "x" : 0.0,
      "y" : -5.6336284,
      "z" : 5.6336284
    }, {
      "x" : -4.5998383,
      "y" : -4.5998383,
      "z" : 4.5998383
    } ],
    "faces" : [ {
      "vertices" : [ 0, 1, 2 ]
    }, {
      "vertices" : [ 0, 2, 1 ]
    } ]
  }, {
    "id" : "59d6e005-6bbe-430f-9741-79eab26afaa1",
    "vertices" : [ {
      "x" : 5.6336284,
      "y" : 5.6336284,
      "z" : 0.0
    }, {
      "x" : 7.5115047,
      "y" : 1.8778762,
      "z" : -1.8778762
    }, {
      "x" : 4.5998383,
      "y" : 4.5998383,
      "z" : -4.5998383
    } ],
    "faces" : [ {
      "vertices" : [ 0, 1, 2 ]
    }, {
      "vertices" : [ 0, 2, 1 ]
    } ]
  }, {
    "id" : "66566b6f-0779-4a9d-8788-98fabe774de7",
    "vertices" : [ {
      "x" : -2.6557178,
      "y" : 5.3114357,
      "z" : -5.3114357
    }, {
      "x" : -5.6336284,
      "y" : 5.6336284,
      "z" : 0.0
    }, {
      "x" : 0.0,
      "y" : 7.967154,
      "z" : 0.0
    } ],
    "faces" : [ {
      "vertices" : [ 0, 1, 2 ]
    }, {
      "vertices" : [ 0, 2, 1 ]
    } ]
  }, {
    "id" : "134fedcc-f78c-433a-a73e-615c9baa06bc",
    "vertices" : [ {
      "x" : 5.6336284,
      "y" : 0.0,
      "z" : -5.6336284
    }, {
      "x" : 4.5998383,
      "y" : 4.5998383,
      "z" : -4.5998383
    }, {
      "x" : 7.5115047,
      "y" : 1.8778762,
      "z" : -1.8778762
    } ],
    "faces" : [ {
      "vertices" : [ 0, 1, 2 ]
    }, {
      "vertices" : [ 0, 2, 1 ]
    } ]
  }, {
    "id" : "90a5fb7e-6098-4540-9c7c-163740d86cb6",
    "vertices" : [ {
      "x" : -5.6336284,
      "y" : 0.0,
      "z" : -5.6336284
    }, {
      "x" : -4.5998383,
      "y" : 4.5998383,
      "z" : -4.5998383
    }, {
      "x" : -7.967154,
      "y" : 0.0,
      "z" : 0.0
    } ],
    "faces" : [ {
      "vertices" : [ 0, 1, 2 ]
    }, {
      "vertices" : [ 0, 2, 1 ]
    } ]
  }, {
    "id" : "34a17914-6ec2-4c42-873e-e0e2c723c5e3",
    "vertices" : [ {
      "x" : 2.6557178,
      "y" : -5.3114357,
      "z" : 5.3114357
    }, {
      "x" : 0.0,
      "y" : -5.6336284,
      "z" : 5.6336284
    }, {
      "x" : -1.8778762,
      "y" : -7.5115047,
      "z" : 1.8778762
    }, {
      "x" : 0.0,
      "y" : -7.967154,
      "z" : 0.0
    } ],
    "faces" : [ {
      "vertices" : [ 0, 1, 2 ]
    }, {
      "vertices" : [ 0, 2, 3 ]
    }, {
      "vertices" : [ 0, 3, 2 ]
    }, {
      "vertices" : [ 0, 2, 1 ]
    } ]
  }, {
    "id" : "fc8ad211-fc2b-4f34-8def-444f7a8d1384",
    "vertices" : [ {
      "x" : 0.0,
      "y" : 7.967154,
      "z" : 0.0
    }, {
      "x" : 0.0,
      "y" : 5.6336284,
      "z" : 5.6336284
    }, {
      "x" : 5.3114357,
      "y" : 5.3114357,
      "z" : 2.6557178
    } ],
    "faces" : [ {
      "vertices" : [ 0, 1, 2 ]
    }, {
      "vertices" : [ 0, 2, 1 ]
    } ]
  }, {
    "id" : "193676cf-3105-4841-98b3-168e61618873",
    "vertices" : [ {
      "x" : 1.8778762,
      "y" : 7.5115047,
      "z" : -1.8778762
    }, {
      "x" : 5.6336284,
      "y" : 5.6336284,
      "z" : 0.0
    }, {
      "x" : 4.5998383,
      "y" : 4.5998383,
      "z" : -4.5998383
    } ],
    "faces" : [ {
      "vertices" : [ 0, 1, 2 ]
    }, {
      "vertices" : [ 0, 2, 1 ]
    } ]
  }, {
    "id" : "7f1b2218-cd7b-4b69-896d-5ee3f04c2e2c",
    "vertices" : [ {
      "x" : -2.6557178,
      "y" : 5.3114357,
      "z" : -5.3114357
    }, {
      "x" : -5.6336284,
      "y" : 0.0,
      "z" : -5.6336284
    }, {
      "x" : -4.5998383,
      "y" : 4.5998383,
      "z" : -4.5998383
    } ],
    "faces" : [ {
      "vertices" : [ 0, 1, 2 ]
    }, {
      "vertices" : [ 0, 2, 1 ]
    } ]
  }, {
    "id" : "37198da4-daf3-4253-93a9-339be560cbb5",
    "vertices" : [ {
      "x" : 5.3114357,
      "y" : -2.6557178,
      "z" : -5.3114357
    }, {
      "x" : 7.967154,
      "y" : 0.0,
      "z" : 0.0
    }, {
      "x" : 5.6336284,
      "y" : -5.6336284,
      "z" : 0.0
    } ],
    "faces" : [ {
      "vertices" : [ 0, 1, 2 ]
    }, {
      "vertices" : [ 0, 2, 1 ]
    } ]
  }, {
    "id" : "83377683-d14c-4acb-9518-dbd85647339f",
    "vertices" : [ {
      "x" : -4.5998383,
      "y" : -4.5998383,
      "z" : -4.5998383
    }, {
      "x" : 0.0,
      "y" : -5.6336284,
      "z" : -5.6336284
    }, {
      "x" : 0.0,
      "y" : 0.0,
      "z" : -7.967154
    } ],
    "faces" : [ {
      "vertices" : [ 0, 1, 2 ]
    }, {
      "vertices" : [ 0, 2, 1 ]
    } ]
  }, {
    "id" : "ffc6a6f6-9a92-455d-b4b1-debdd8039566",
    "vertices" : [ {
      "x" : 5.3114357,
      "y" : -2.6557178,
      "z" : -5.3114357
    }, {
      "x" : 0.0,
      "y" : -5.6336284,
      "z" : -5.6336284
    }, {
      "x" : 0.0,
      "y" : 0.0,
      "z" : -7.967154
    } ],
    "faces" : [ {
      "vertices" : [ 0, 1, 2 ]
    }, {
      "vertices" : [ 0, 2, 1 ]
    } ]
  }, {
    "id" : "ba6f728e-2820-4df1-8832-744c90f08c4c",
    "vertices" : [ {
      "x" : 2.6557178,
      "y" : -5.3114357,
      "z" : 5.3114357
    }, {
      "x" : 5.6336284,
      "y" : -5.6336284,
      "z" : 0.0
    }, {
      "x" : 4.5998383,
      "y" : -4.5998383,
      "z" : 4.5998383
    } ],
    "faces" : [ {
      "vertices" : [ 0, 1, 2 ]
    }, {
      "vertices" : [ 0, 2, 1 ]
    } ]
  }, {
    "id" : "e8c36a3d-5239-41fb-9147-32c87103055b",
    "vertices" : [ {
      "x" : -5.3114357,
      "y" : 2.6557178,
      "z" : 5.3114357
    }, {
      "x" : -7.967154,
      "y" : 0.0,
      "z" : 0.0
    }, {
      "x" : -7.5115047,
      "y" : -1.8778762,
      "z" : 1.8778762
    }, {
      "x" : -5.6336284,
      "y" : 0.0,
      "z" : 5.6336284
    } ],
    "faces" : [ {
      "vertices" : [ 0, 1, 2 ]
    }, {
      "vertices" : [ 0, 2, 3 ]
    }, {
      "vertices" : [ 0, 3, 2 ]
    }, {
      "vertices" : [ 0, 2, 1 ]
    } ]
  }, {
    "id" : "458f19eb-88fa-4adc-9b1d-acf07035876f",
    "vertices" : [ {
      "x" : 1.8778762,
      "y" : 1.8778762,
      "z" : -7.5115047
    }, {
      "x" : 4.5998383,
      "y" : 4.5998383,
      "z" : -4.5998383
    }, {
      "x" : 5.6336284,
      "y" : 0.0,
      "z" : -5.6336284
    } ],
    "faces" : [ {
      "vertices" : [ 0, 1, 2 ]
    }, {
      "vertices" : [ 0, 2, 1 ]
    } ]
  }, {
    "id" : "403dfc9e-2e69-4f4b-ad5d-579b3c91cd1f",
    "vertices" : [ {
      "x" : 2.6557178,
      "y" : -5.3114357,
      "z" : 5.3114357
    }, {
      "x" : 5.6336284,
      "y" : 0.0,
      "z" : 5.6336284
    }, {
      "x" : 0.0,
      "y" : 0.0,
      "z" : 7.967154
    } ],
    "faces" : [ {
      "vertices" : [ 0, 1, 2 ]
    }, {
      "vertices" : [ 0, 2, 1 ]
    } ]
  }, {
    "id" : "d560a341-7fb3-4225-a50a-6d1aa86090b1",
    "vertices" : [ {
      "x" : -2.6557178,
      "y" : 5.3114357,
      "z" : -5.3114357
    }, {
      "x" : -4.5998383,
      "y" : 4.5998383,
      "z" : -4.5998383
    }, {
      "x" : -5.6336284,
      "y" : 5.6336284,
      "z" : 0.0
    } ],
    "faces" : [ {
      "vertices" : [ 0, 1, 2 ]
    }, {
      "vertices" : [ 0, 2, 1 ]
    } ]
  }, {
    "id" : "cf716546-cdb6-4779-8c79-b3cbe1b4cd12",
    "vertices" : [ {
      "x" : 1.8778762,
      "y" : 7.5115047,
      "z" : -1.8778762
    }, {
      "x" : 0.0,
      "y" : 7.967154,
      "z" : 0.0
    }, {
      "x" : 5.3114357,
      "y" : 5.3114357,
      "z" : 2.6557178
    }, {
      "x" : 5.6336284,
      "y" : 5.6336284,
      "z" : 0.0
    } ],
    "faces" : [ {
      "vertices" : [ 0, 1, 2 ]
    }, {
      "vertices" : [ 0, 2, 3 ]
    }, {
      "vertices" : [ 0, 3, 2 ]
    }, {
      "vertices" : [ 0, 2, 1 ]
    } ]
  }, {
    "id" : "f473c35e-c207-4151-842f-4af5d08a8645",
    "vertices" : [ {
      "x" : 4.5998383,
      "y" : -4.5998383,
      "z" : 4.5998383
    }, {
      "x" : 5.6336284,
      "y" : 0.0,
      "z" : 5.6336284
    }, {
      "x" : 7.967154,
      "y" : 0.0,
      "z" : 0.0
    } ],
    "faces" : [ {
      "vertices" : [ 0, 1, 2 ]
    }, {
      "vertices" : [ 0, 2, 1 ]
    } ]
  }, {
    "id" : "928f2b8f-617e-4040-80f0-24558a5d808d",
    "vertices" : [ {
      "x" : 5.6336284,
      "y" : 5.6336284,
      "z" : 0.0
    }, {
      "x" : 5.3114357,
      "y" : 5.3114357,
      "z" : 2.6557178
    }, {
      "x" : 7.967154,
      "y" : 0.0,
      "z" : 0.0
    }, {
      "x" : 7.5115047,
      "y" : 1.8778762,
      "z" : -1.8778762
    } ],
    "faces" : [ {
      "vertices" : [ 0, 1, 2 ]
    }, {
      "vertices" : [ 0, 2, 3 ]
    }, {
      "vertices" : [ 0, 3, 2 ]
    }, {
      "vertices" : [ 0, 2, 1 ]
    } ]
  }, {
    "id" : "1b1e2287-287d-46f0-8a72-4e924a5c3a53",
    "vertices" : [ {
      "x" : 4.5998383,
      "y" : 4.5998383,
      "z" : 4.5998383
    }, {
      "x" : 5.6336284,
      "y" : 0.0,
      "z" : 5.6336284
    }, {
      "x" : 5.3114357,
      "y" : 5.3114357,
      "z" : 2.6557178
    } ],
    "faces" : [ {
      "vertices" : [ 0, 1, 2 ]
    }, {
      "vertices" : [ 0, 2, 1 ]
    } ]
  }, {
    "id" : "0126f785-7367-42da-858b-4984ab136c51",
    "vertices" : [ {
      "x" : -5.3114357,
      "y" : 2.6557178,
      "z" : 5.3114357
    }, {
      "x" : 0.0,
      "y" : 0.0,
      "z" : 7.967154
    }, {
      "x" : 0.0,
      "y" : 5.6336284,
      "z" : 5.6336284
    } ],
    "faces" : [ {
      "vertices" : [ 0, 1, 2 ]
    }, {
      "vertices" : [ 0, 2, 1 ]
    } ]
  }, {
    "id" : "2c8e32f4-4c82-46ea-8224-82065deec7a5",
    "vertices" : [ {
      "x" : -2.6557178,
      "y" : 5.3114357,
      "z" : -5.3114357
    }, {
      "x" : 0.0,
      "y" : 5.6336284,
      "z" : -5.6336284
    }, {
      "x" : 1.8778762,
      "y" : 1.8778762,
      "z" : -7.5115047
    }, {
      "x" : 0.0,
      "y" : 0.0,
      "z" : -7.967154
    } ],
    "faces" : [ {
      "vertices" : [ 0, 1, 2 ]
    }, {
      "vertices" : [ 0, 2, 3 ]
    }, {
      "vertices" : [ 0, 3, 2 ]
    }, {
      "vertices" : [ 0, 2, 1 ]
    } ]
  }, {
    "id" : "30a0aea5-7bfd-4d15-a597-f29b463af136",
    "vertices" : [ {
      "x" : 0.0,
      "y" : 5.6336284,
      "z" : 5.6336284
    }, {
      "x" : 4.5998383,
      "y" : 4.5998383,
      "z" : 4.5998383
    }, {
      "x" : 0.0,
      "y" : 0.0,
      "z" : 7.967154
    } ],
    "faces" : [ {
      "vertices" : [ 0, 1, 2 ]
    }, {
      "vertices" : [ 0, 2, 1 ]
    } ]
  }, {
    "id" : "a192d036-4258-4972-ab06-11d9fcaee28e",
    "vertices" : [ {
      "x" : 4.5998383,
      "y" : 4.5998383,
      "z" : 4.5998383
    }, {
      "x" : 5.3114357,
      "y" : 5.3114357,
      "z" : 2.6557178
    }, {
      "x" : 0.0,
      "y" : 5.6336284,
      "z" : 5.6336284
    } ],
    "faces" : [ {
      "vertices" : [ 0, 1, 2 ]
    }, {
      "vertices" : [ 0, 2, 1 ]
    } ]
  }, {
    "id" : "a3dfab56-12f5-435c-b9d7-cf8edb1db528",
    "vertices" : [ {
      "x" : -5.6336284,
      "y" : 0.0,
      "z" : -5.6336284
    }, {
      "x" : -5.3114357,
      "y" : -5.3114357,
      "z" : -2.6557178
    }, {
      "x" : -7.967154,
      "y" : 0.0,
      "z" : 0.0
    } ],
    "faces" : [ {
      "vertices" : [ 0, 1, 2 ]
    }, {
      "vertices" : [ 0, 2, 1 ]
    } ]
  }, {
    "id" : "057b268f-2a3f-4df9-b0e0-c65440165e31",
    "vertices" : [ {
      "x" : 0.0,
      "y" : -5.6336284,
      "z" : -5.6336284
    }, {
      "x" : 0.0,
      "y" : -7.967154,
      "z" : 0.0
    }, {
      "x" : 4.5998383,
      "y" : -4.5998383,
      "z" : -4.5998383
    } ],
    "faces" : [ {
      "vertices" : [ 0, 1, 2 ]
    }, {
      "vertices" : [ 0, 2, 1 ]
    } ]
  }, {
    "id" : "42722eea-4aad-4116-a6dd-9a7af2d55354",
    "vertices" : [ {
      "x" : 5.6336284,
      "y" : -5.6336284,
      "z" : 0.0
    }, {
      "x" : 4.5998383,
      "y" : -4.5998383,
      "z" : -4.5998383
    }, {
      "x" : 0.0,
      "y" : -7.967154,
      "z" : 0.0
    } ],
    "faces" : [ {
      "vertices" : [ 0, 1, 2 ]
    }, {
      "vertices" : [ 0, 2, 1 ]
    } ]
  }, {
    "id" : "08e773d6-0b06-4a96-8095-f9ee9843964f",
    "vertices" : [ {
      "x" : -1.8778762,
      "y" : -1.8778762,
      "z" : 7.5115047
    }, {
      "x" : -4.5998383,
      "y" : -4.5998383,
      "z" : 4.5998383
    }, {
      "x" : 0.0,
      "y" : -5.6336284,
      "z" : 5.6336284
    } ],
    "faces" : [ {
      "vertices" : [ 0, 1, 2 ]
    }, {
      "vertices" : [ 0, 2, 1 ]
    } ]
  }, {
    "id" : "0e5914b3-4efe-49b9-a75e-8f4de7a990f2",
    "vertices" : [ {
      "x" : -2.6557178,
      "y" : 5.3114357,
      "z" : -5.3114357
    }, {
      "x" : 0.0,
      "y" : 0.0,
      "z" : -7.967154
    }, {
      "x" : -5.6336284,
      "y" : 0.0,
      "z" : -5.6336284
    } ],
    "faces" : [ {
      "vertices" : [ 0, 1, 2 ]
    }, {
      "vertices" : [ 0, 2, 1 ]
    } ]
  }, {
    "id" : "c58ce1f2-ae4d-43ae-8c3b-cac1eaf63fc3",
    "vertices" : [ {
      "x" : 5.3114357,
      "y" : -2.6557178,
      "z" : -5.3114357
    }, {
      "x" : 5.6336284,
      "y" : -5.6336284,
      "z" : 0.0
    }, {
      "x" : 4.5998383,
      "y" : -4.5998383,
      "z" : -4.5998383
    } ],
    "faces" : [ {
      "vertices" : [ 0, 1, 2 ]
    }, {
      "vertices" : [ 0, 2, 1 ]
    } ]
  }, {
    "id" : "d539a4f2-9b06-4f56-a4c8-5afe400cb07c",
    "vertices" : [ {
      "x" : 2.6557178,
      "y" : -5.3114357,
      "z" : 5.3114357
    }, {
      "x" : 0.0,
      "y" : -7.967154,
      "z" : 0.0
    }, {
      "x" : 5.6336284,
      "y" : -5.6336284,
      "z" : 0.0
    } ],
    "faces" : [ {
      "vertices" : [ 0, 1, 2 ]
    }, {
      "vertices" : [ 0, 2, 1 ]
    } ]
  } ],
  "instances" : [ {
    "shape" : "8831d3d1-717a-4f33-b37e-f688cd59eade",
    "color" : "#FFFFFF",
    "position" : {
      "x" : 0.0,
      "y" : 0.0,
      "z" : 0.0
    }
  }, {
    "shape" : "37df7afd-353c-4ab6-afff-57f11ec9131f",
    "color" : "#008D36",
    "position" : {
      "x" : 0.0,
      "y" : 5.6336284,
      "z" : -5.6336284
    }
  }, {
    "shape" : "3d88162b-b08c-4059-951c-79167ca70f8f",
    "color" : "#FFFFFF",
    "position" : {
      "x" : 0.0,
      "y" : 0.0,
      "z" : 0.0
    }
  }, {
    "shape" : "ae6d8e5c-1b79-4358-9979-cddd44a68e2c",
    "color" : "#FFFFFF",
    "position" : {
      "x" : 0.0,
      "y" : 0.0,
      "z" : 0.0
    }
  }, {
    "shape" : "37df7afd-353c-4ab6-afff-57f11ec9131f",
    "color" : "#F0A000",
    "position" : {
      "x" : 4.5998383,
      "y" : 4.5998383,
      "z" : 4.5998383
    }
  }, {
    "shape" : "ae3b6adb-44f5-4937-8bb5-911baacedd85",
    "color" : "#FFFFFF",
    "position" : {
      "x" : 0.0,
      "y" : 0.0,
      "z" : 0.0
    }
  }, {
    "shape" : "37df7afd-353c-4ab6-afff-57f11ec9131f",
    "color" : "#F0A000",
    "position" : {
      "x" : 4.5998383,
      "y" : -4.5998383,
      "z" : 4.5998383
    }
  }, {
    "shape" : "ac2bcaca-4e04-4f67-b58a-a59931c18a4b",
    "color" : "#FFFFFF",
    "position" : {
      "x" : 0.0,
      "y" : 0.0,
      "z" : 0.0
    }
  }, {
    "shape" : "9e535c97-b82f-4592-8c89-74e628f274cd",
    "color" : "#666666",
    "position" : {
      "x" : 0.0,
      "y" : 0.0,
      "z" : 0.0
    }
  }, {
    "shape" : "ed2e9538-f6dd-440e-b8c4-8364cfea64e2",
    "color" : "#FFFFFF",
    "position" : {
      "x" : 0.0,
      "y" : 0.0,
      "z" : 0.0
    }
  }, {
    "shape" : "37df7afd-353c-4ab6-afff-57f11ec9131f",
    "color" : "#FFFFFF",
    "position" : {
      "x" : 5.3114357,
      "y" : 5.3114357,
      "z" : 2.6557178
    }
  }, {
    "shape" : "37df7afd-353c-4ab6-afff-57f11ec9131f",
    "color" : "#FFFFFF",
    "position" : {
      "x" : 7.5115047,
      "y" : 1.8778762,
      "z" : -1.8778762
    }
  }, {
    "shape" : "dac3063f-28a7-41b0-a1bb-46a277882306",
    "color" : "#666666",
    "position" : {
      "x" : 0.0,
      "y" : 0.0,
      "z" : 0.0
    }
  }, {
    "shape" : "71d4bade-199b-4087-a425-817a81da87b4",
    "color" : "#FFFFFF",
    "position" : {
      "x" : 0.0,
      "y" : 0.0,
      "z" : 0.0
    }
  }, {
    "shape" : "f52e5f75-b5a9-41e7-80e5-6fb37478c352",
    "color" : "#FFFFFF",
    "position" : {
      "x" : 0.0,
      "y" : 0.0,
      "z" : 0.0
    }
  }, {
    "shape" : "36342bf4-a482-42dd-be91-c5a0c364798c",
    "color" : "#FFFFFF",
    "position" : {
      "x" : 0.0,
      "y" : 0.0,
      "z" : 0.0
    }
  }, {
    "shape" : "718d5dd3-0cdd-435b-9228-1f3b9af6a50a",
    "color" : "#FFFFFF",
    "position" : {
      "x" : 0.0,
      "y" : 0.0,
      "z" : 0.0
    }
  }, {
    "shape" : "75e9cbba-e42f-4aee-94a9-2ecd302157e4",
    "color" : "#FFFFFF",
    "position" : {
      "x" : 0.0,
      "y" : 0.0,
      "z" : 0.0
    }
  }, {
    "shape" : "d92f8a65-cd28-456e-b1e7-3271dd07b210",
    "color" : "#FFFFFF",
    "position" : {
      "x" : 0.0,
      "y" : 0.0,
      "z" : 0.0
    }
  }, {
    "shape" : "37df7afd-353c-4ab6-afff-57f11ec9131f",
    "color" : "#008D36",
    "position" : {
      "x" : -5.6336284,
      "y" : 0.0,
      "z" : 5.6336284
    }
  }, {
    "shape" : "3f262954-a4fb-4fd7-8744-aec6dc2c34d2",
    "color" : "#FFFFFF",
    "position" : {
      "x" : 0.0,
      "y" : 0.0,
      "z" : 0.0
    }
  }, {
    "shape" : "5014e9d8-e2f2-4bc3-b322-f19923101982",
    "color" : "#FFFFFF",
    "position" : {
      "x" : 0.0,
      "y" : 0.0,
      "z" : 0.0
    }
  }, {
    "shape" : "37df7afd-353c-4ab6-afff-57f11ec9131f",
    "color" : "#FFFFFF",
    "position" : {
      "x" : -2.6557178,
      "y" : 5.3114357,
      "z" : -5.3114357
    }
  }, {
    "shape" : "d0e05b00-8f11-4056-9729-57dcdda1c7ee",
    "color" : "#FFFFFF",
    "position" : {
      "x" : 0.0,
      "y" : 0.0,
      "z" : 0.0
    }
  }, {
    "shape" : "37df7afd-353c-4ab6-afff-57f11ec9131f",
    "color" : "#008D36",
    "position" : {
      "x" : 5.6336284,
      "y" : 5.6336284,
      "z" : 0.0
    }
  }, {
    "shape" : "dd13bcf9-4a07-4a60-b2ad-dd9a0149d3b2",
    "color" : "#FFFFFF",
    "position" : {
      "x" : 0.0,
      "y" : 0.0,
      "z" : 0.0
    }
  }, {
    "shape" : "a0e0c217-88e4-406e-b92b-d0fd971feea2",
    "color" : "#FFFFFF",
    "position" : {
      "x" : 0.0,
      "y" : 0.0,
      "z" : 0.0
    }
  }, {
    "shape" : "eba009e8-8b42-485d-aded-d0aabc05b740",
    "color" : "#FFFFFF",
    "position" : {
      "x" : 0.0,
      "y" : 0.0,
      "z" : 0.0
    }
  }, {
    "shape" : "37df7afd-353c-4ab6-afff-57f11ec9131f",
    "color" : "#F0A000",
    "position" : {
      "x" : 4.5998383,
      "y" : 4.5998383,
      "z" : -4.5998383
    }
  }, {
    "shape" : "4941e416-eb94-472d-8134-cd399de6f072",
    "color" : "#FFFFFF",
    "position" : {
      "x" : 0.0,
      "y" : 0.0,
      "z" : 0.0
    }
  }, {
    "shape" : "37df7afd-353c-4ab6-afff-57f11ec9131f",
    "color" : "#FFFFFF",
    "position" : {
      "x" : 1.8778762,
      "y" : 1.8778762,
      "z" : -7.5115047
    }
  }, {
    "shape" : "5ee63fb7-e96f-41c3-8008-f818a5aa3aeb",
    "color" : "#FFFFFF",
    "position" : {
      "x" : 0.0,
      "y" : 0.0,
      "z" : 0.0
    }
  }, {
    "shape" : "37df7afd-353c-4ab6-afff-57f11ec9131f",
    "color" : "#008D36",
    "position" : {
      "x" : 5.6336284,
      "y" : 0.0,
      "z" : -5.6336284
    }
  }, {
    "shape" : "37df7afd-353c-4ab6-afff-57f11ec9131f",
    "color" : "#FFFFFF",
    "position" : {
      "x" : -7.5115047,
      "y" : -1.8778762,
      "z" : 1.8778762
    }
  }, {
    "shape" : "dc8cacfc-dd32-4fce-9fa0-000ebe8f6bb1",
    "color" : "#FFFFFF",
    "position" : {
      "x" : 0.0,
      "y" : 0.0,
      "z" : 0.0
    }
  }, {
    "shape" : "4986bdb6-750a-4d89-9bee-62098c2f3d0f",
    "color" : "#FFFFFF",
    "position" : {
      "x" : 0.0,
      "y" : 0.0,
      "z" : 0.0
    }
  }, {
    "shape" : "094bc9ca-a4b0-48cb-8e0c-77a4e1087998",
    "color" : "#666666",
    "position" : {
      "x" : 0.0,
      "y" : 0.0,
      "z" : 0.0
    }
  }, {
    "shape" : "88199e92-0120-4365-a675-edc8ab7ee882",
    "color" : "#FFFFFF",
    "position" : {
      "x" : 0.0,
      "y" : 0.0,
      "z" : 0.0
    }
  }, {
    "shape" : "37df7afd-353c-4ab6-afff-57f11ec9131f",
    "color" : "#F0A000",
    "position" : {
      "x" : -4.5998383,
      "y" : -4.5998383,
      "z" : 4.5998383
    }
  }, {
    "shape" : "37df7afd-353c-4ab6-afff-57f11ec9131f",
    "color" : "#FFFFFF",
    "position" : {
      "x" : -5.3114357,
      "y" : -5.3114357,
      "z" : -2.6557178
    }
  }, {
    "shape" : "bf93f6b4-4b84-44bb-99ea-91edacc5363c",
    "color" : "#FFFFFF",
    "position" : {
      "x" : 0.0,
      "y" : 0.0,
      "z" : 0.0
    }
  }, {
    "shape" : "37df7afd-353c-4ab6-afff-57f11ec9131f",
    "color" : "#008D36",
    "position" : {
      "x" : 0.0,
      "y" : 5.6336284,
      "z" : 5.6336284
    }
  }, {
    "shape" : "37df7afd-353c-4ab6-afff-57f11ec9131f",
    "color" : "#FFFFFF",
    "position" : {
      "x" : 1.8778762,
      "y" : 7.5115047,
      "z" : -1.8778762
    }
  }, {
    "shape" : "37df7afd-353c-4ab6-afff-57f11ec9131f",
    "color" : "#008D36",
    "position" : {
      "x" : -5.6336284,
      "y" : 5.6336284,
      "z" : 0.0
    }
  }, {
    "shape" : "9e31514b-4178-417d-a5d3-5d395728d700",
    "color" : "#FFFFFF",
    "position" : {
      "x" : 0.0,
      "y" : 0.0,
      "z" : 0.0
    }
  }, {
    "shape" : "f32b3079-b201-460e-a179-39595de87291",
    "color" : "#FFFFFF",
    "position" : {
      "x" : 0.0,
      "y" : 0.0,
      "z" : 0.0
    }
  }, {
    "shape" : "59d6e005-6bbe-430f-9741-79eab26afaa1",
    "color" : "#FFFFFF",
    "position" : {
      "x" : 0.0,
      "y" : 0.0,
      "z" : 0.0
    }
  }, {
    "shape" : "66566b6f-0779-4a9d-8788-98fabe774de7",
    "color" : "#FFFFFF",
    "position" : {
      "x" : 0.0,
      "y" : 0.0,
      "z" : 0.0
    }
  }, {
    "shape" : "37df7afd-353c-4ab6-afff-57f11ec9131f",
    "color" : "#008D36",
    "position" : {
      "x" : -5.6336284,
      "y" : -5.6336284,
      "z" : 0.0
    }
  }, {
    "shape" : "37df7afd-353c-4ab6-afff-57f11ec9131f",
    "color" : "#007695",
    "position" : {
      "x" : 0.0,
      "y" : 7.967154,
      "z" : 0.0
    }
  }, {
    "shape" : "134fedcc-f78c-433a-a73e-615c9baa06bc",
    "color" : "#FFFFFF",
    "position" : {
      "x" : 0.0,
      "y" : 0.0,
      "z" : 0.0
    }
  }, {
    "shape" : "90a5fb7e-6098-4540-9c7c-163740d86cb6",
    "color" : "#666666",
    "position" : {
      "x" : 0.0,
      "y" : 0.0,
      "z" : 0.0
    }
  }, {
    "shape" : "37df7afd-353c-4ab6-afff-57f11ec9131f",
    "color" : "#007695",
    "position" : {
      "x" : 0.0,
      "y" : 0.0,
      "z" : -7.967154
    }
  }, {
    "shape" : "37df7afd-353c-4ab6-afff-57f11ec9131f",
    "color" : "#008D36",
    "position" : {
      "x" : 5.6336284,
      "y" : 0.0,
      "z" : 5.6336284
    }
  }, {
    "shape" : "37df7afd-353c-4ab6-afff-57f11ec9131f",
    "color" : "#FFFFFF",
    "position" : {
      "x" : 5.3114357,
      "y" : -2.6557178,
      "z" : -5.3114357
    }
  }, {
    "shape" : "37df7afd-353c-4ab6-afff-57f11ec9131f",
    "color" : "#F0A000",
    "position" : {
      "x" : 4.5998383,
      "y" : -4.5998383,
      "z" : -4.5998383
    }
  }, {
    "shape" : "34a17914-6ec2-4c42-873e-e0e2c723c5e3",
    "color" : "#FFFFFF",
    "position" : {
      "x" : 0.0,
      "y" : 0.0,
      "z" : 0.0
    }
  }, {
    "shape" : "37df7afd-353c-4ab6-afff-57f11ec9131f",
    "color" : "#FFFFFF",
    "position" : {
      "x" : 2.6557178,
      "y" : -5.3114357,
      "z" : 5.3114357
    }
  }, {
    "shape" : "fc8ad211-fc2b-4f34-8def-444f7a8d1384",
    "color" : "#FFFFFF",
    "position" : {
      "x" : 0.0,
      "y" : 0.0,
      "z" : 0.0
    }
  }, {
    "shape" : "193676cf-3105-4841-98b3-168e61618873",
    "color" : "#FFFFFF",
    "position" : {
      "x" : 0.0,
      "y" : 0.0,
      "z" : 0.0
    }
  }, {
    "shape" : "7f1b2218-cd7b-4b69-896d-5ee3f04c2e2c",
    "color" : "#FFFFFF",
    "position" : {
      "x" : 0.0,
      "y" : 0.0,
      "z" : 0.0
    }
  }, {
    "shape" : "37198da4-daf3-4253-93a9-339be560cbb5",
    "color" : "#FFFFFF",
    "position" : {
      "x" : 0.0,
      "y" : 0.0,
      "z" : 0.0
    }
  }, {
    "shape" : "37df7afd-353c-4ab6-afff-57f11ec9131f",
    "color" : "#FFFFFF",
    "position" : {
      "x" : -1.8778762,
      "y" : -1.8778762,
      "z" : 7.5115047
    }
  }, {
    "shape" : "83377683-d14c-4acb-9518-dbd85647339f",
    "color" : "#FFFFFF",
    "position" : {
      "x" : 0.0,
      "y" : 0.0,
      "z" : 0.0
    }
  }, {
    "shape" : "ffc6a6f6-9a92-455d-b4b1-debdd8039566",
    "color" : "#FFFFFF",
    "position" : {
      "x" : 0.0,
      "y" : 0.0,
      "z" : 0.0
    }
  }, {
    "shape" : "ba6f728e-2820-4df1-8832-744c90f08c4c",
    "color" : "#FFFFFF",
    "position" : {
      "x" : 0.0,
      "y" : 0.0,
      "z" : 0.0
    }
  }, {
    "shape" : "37df7afd-353c-4ab6-afff-57f11ec9131f",
    "color" : "#008D36",
    "position" : {
      "x" : 5.6336284,
      "y" : -5.6336284,
      "z" : 0.0
    }
  }, {
    "shape" : "e8c36a3d-5239-41fb-9147-32c87103055b",
    "color" : "#FFFFFF",
    "position" : {
      "x" : 0.0,
      "y" : 0.0,
      "z" : 0.0
    }
  }, {
    "shape" : "458f19eb-88fa-4adc-9b1d-acf07035876f",
    "color" : "#FFFFFF",
    "position" : {
      "x" : 0.0,
      "y" : 0.0,
      "z" : 0.0
    }
  }, {
    "shape" : "403dfc9e-2e69-4f4b-ad5d-579b3c91cd1f",
    "color" : "#FFFFFF",
    "position" : {
      "x" : 0.0,
      "y" : 0.0,
      "z" : 0.0
    }
  }, {
    "shape" : "d560a341-7fb3-4225-a50a-6d1aa86090b1",
    "color" : "#FFFFFF",
    "position" : {
      "x" : 0.0,
      "y" : 0.0,
      "z" : 0.0
    }
  }, {
    "shape" : "cf716546-cdb6-4779-8c79-b3cbe1b4cd12",
    "color" : "#FFFFFF",
    "position" : {
      "x" : 0.0,
      "y" : 0.0,
      "z" : 0.0
    }
  }, {
    "shape" : "37df7afd-353c-4ab6-afff-57f11ec9131f",
    "color" : "#008D36",
    "position" : {
      "x" : -5.6336284,
      "y" : 0.0,
      "z" : -5.6336284
    }
  }, {
    "shape" : "f473c35e-c207-4151-842f-4af5d08a8645",
    "color" : "#FFFFFF",
    "position" : {
      "x" : 0.0,
      "y" : 0.0,
      "z" : 0.0
    }
  }, {
    "shape" : "928f2b8f-617e-4040-80f0-24558a5d808d",
    "color" : "#FFFFFF",
    "position" : {
      "x" : 0.0,
      "y" : 0.0,
      "z" : 0.0
    }
  }, {
    "shape" : "1b1e2287-287d-46f0-8a72-4e924a5c3a53",
    "color" : "#FFFFFF",
    "position" : {
      "x" : 0.0,
      "y" : 0.0,
      "z" : 0.0
    }
  }, {
    "shape" : "37df7afd-353c-4ab6-afff-57f11ec9131f",
    "color" : "#008D36",
    "position" : {
      "x" : 0.0,
      "y" : -5.6336284,
      "z" : 5.6336284
    }
  }, {
    "shape" : "0126f785-7367-42da-858b-4984ab136c51",
    "color" : "#FFFFFF",
    "position" : {
      "x" : 0.0,
      "y" : 0.0,
      "z" : 0.0
    }
  }, {
    "shape" : "2c8e32f4-4c82-46ea-8224-82065deec7a5",
    "color" : "#FFFFFF",
    "position" : {
      "x" : 0.0,
      "y" : 0.0,
      "z" : 0.0
    }
  }, {
    "shape" : "37df7afd-353c-4ab6-afff-57f11ec9131f",
    "color" : "#007695",
    "position" : {
      "x" : 0.0,
      "y" : -7.967154,
      "z" : 0.0
    }
  }, {
    "shape" : "37df7afd-353c-4ab6-afff-57f11ec9131f",
    "color" : "#FFFFFF",
    "position" : {
      "x" : -1.8778762,
      "y" : -7.5115047,
      "z" : 1.8778762
    }
  }, {
    "shape" : "37df7afd-353c-4ab6-afff-57f11ec9131f",
    "color" : "#007695",
    "position" : {
      "x" : 0.0,
      "y" : 0.0,
      "z" : 7.967154
    }
  }, {
    "shape" : "37df7afd-353c-4ab6-afff-57f11ec9131f",
    "color" : "#008D36",
    "position" : {
      "x" : 0.0,
      "y" : -5.6336284,
      "z" : -5.6336284
    }
  }, {
    "shape" : "30a0aea5-7bfd-4d15-a597-f29b463af136",
    "color" : "#666666",
    "position" : {
      "x" : 0.0,
      "y" : 0.0,
      "z" : 0.0
    }
  }, {
    "shape" : "a192d036-4258-4972-ab06-11d9fcaee28e",
    "color" : "#FFFFFF",
    "position" : {
      "x" : 0.0,
      "y" : 0.0,
      "z" : 0.0
    }
  }, {
    "shape" : "a3dfab56-12f5-435c-b9d7-cf8edb1db528",
    "color" : "#FFFFFF",
    "position" : {
      "x" : 0.0,
      "y" : 0.0,
      "z" : 0.0
    }
  }, {
    "shape" : "057b268f-2a3f-4df9-b0e0-c65440165e31",
    "color" : "#FFFFFF",
    "position" : {
      "x" : 0.0,
      "y" : 0.0,
      "z" : 0.0
    }
  }, {
    "shape" : "37df7afd-353c-4ab6-afff-57f11ec9131f",
    "color" : "#F0A000",
    "position" : {
      "x" : -4.5998383,
      "y" : 4.5998383,
      "z" : 4.5998383
    }
  }, {
    "shape" : "37df7afd-353c-4ab6-afff-57f11ec9131f",
    "color" : "#F0A000",
    "position" : {
      "x" : -4.5998383,
      "y" : 4.5998383,
      "z" : -4.5998383
    }
  }, {
    "shape" : "37df7afd-353c-4ab6-afff-57f11ec9131f",
    "color" : "#FFFFFF",
    "position" : {
      "x" : -5.3114357,
      "y" : 2.6557178,
      "z" : 5.3114357
    }
  }, {
    "shape" : "37df7afd-353c-4ab6-afff-57f11ec9131f",
    "color" : "#F0A000",
    "position" : {
      "x" : -4.5998383,
      "y" : -4.5998383,
      "z" : -4.5998383
    }
  }, {
    "shape" : "42722eea-4aad-4116-a6dd-9a7af2d55354",
    "color" : "#666666",
    "position" : {
      "x" : 0.0,
      "y" : 0.0,
      "z" : 0.0
    }
  }, {
    "shape" : "08e773d6-0b06-4a96-8095-f9ee9843964f",
    "color" : "#FFFFFF",
    "position" : {
      "x" : 0.0,
      "y" : 0.0,
      "z" : 0.0
    }
  }, {
    "shape" : "0e5914b3-4efe-49b9-a75e-8f4de7a990f2",
    "color" : "#FFFFFF",
    "position" : {
      "x" : 0.0,
      "y" : 0.0,
      "z" : 0.0
    }
  }, {
    "shape" : "c58ce1f2-ae4d-43ae-8c3b-cac1eaf63fc3",
    "color" : "#FFFFFF",
    "position" : {
      "x" : 0.0,
      "y" : 0.0,
      "z" : 0.0
    }
  }, {
    "shape" : "d539a4f2-9b06-4f56-a4c8-5afe400cb07c",
    "color" : "#FFFFFF",
    "position" : {
      "x" : 0.0,
      "y" : 0.0,
      "z" : 0.0
    }
  }, {
    "shape" : "37df7afd-353c-4ab6-afff-57f11ec9131f",
    "color" : "#007695",
    "position" : {
      "x" : -7.967154,
      "y" : 0.0,
      "z" : 0.0
    }
  }, {
    "shape" : "37df7afd-353c-4ab6-afff-57f11ec9131f",
    "color" : "#007695",
    "position" : {
      "x" : 7.967154,
      "y" : 0.0,
      "z" : 0.0
    }
  } ]
}